[
   {
      "_links" : {
         "html" : {
            "href" : "https://github.com/bitcoin/bitcoin/pull/3592#discussion_r9221977"
         },
         "pull_request" : {
            "href" : "https://api.github.com/repos/bitcoin/bitcoin/pulls/3592"
         },
         "self" : {
            "href" : "https://api.github.com/repos/bitcoin/bitcoin/pulls/comments/9221977"
         }
      },
      "author_association" : "MEMBER",
      "body" : "This looks like a kind of chimera of the old string and the \"standard rejection reason\" from BIP22. How does this work in practice, is only the initial part matched to the 'Reason' table in https://github.com/bitcoin/bips/blob/master/bip-0022.mediawiki?\nShould we be consistent and use either the minus-delimited-style or the space delimited style of message?\n",
      "commit_id" : "c117d9e93a712c3f1e2001bdb6e20e7a1c5e339b",
      "created_at" : "2014-01-28T09:58:25Z",
      "diff_hunk" : "@@ -605,14 +605,14 @@ bool CheckTransaction(const CTransaction& tx, CValidationState &state)\n     // Basic checks that don't depend on any context\n     if (tx.vin.empty())\n         return state.DoS(10, error(\"CheckTransaction() : vin empty\"),\n-                         REJECT_INVALID, \"vin empty\");\n+                         REJECT_INVALID, \"bad-txns-vin empty\");",
      "html_url" : "https://github.com/bitcoin/bitcoin/pull/3592#discussion_r9221977",
      "id" : 9221977,
      "line" : null,
      "node_id" : "MDI0OlB1bGxSZXF1ZXN0UmV2aWV3Q29tbWVudDkyMjE5Nzc=",
      "original_commit_id" : "0da64dfdb2a41eee2cc4b63703c2962cf269a6ee",
      "original_line" : null,
      "original_position" : 5,
      "original_start_line" : null,
      "path" : "src/main.cpp",
      "position" : null,
      "pull_request_review_id" : null,
      "pull_request_url" : "https://api.github.com/repos/bitcoin/bitcoin/pulls/3592",
      "reactions" : {
         "+1" : 0,
         "-1" : 0,
         "confused" : 0,
         "eyes" : 0,
         "heart" : 0,
         "hooray" : 0,
         "laugh" : 0,
         "rocket" : 0,
         "total_count" : 0,
         "url" : "https://api.github.com/repos/bitcoin/bitcoin/pulls/comments/9221977/reactions"
      },
      "side" : "RIGHT",
      "start_line" : null,
      "start_side" : null,
      "subject_type" : "line",
      "updated_at" : "2014-01-29T17:39:53Z",
      "url" : "https://api.github.com/repos/bitcoin/bitcoin/pulls/comments/9221977",
      "user" : {
         "avatar_url" : "https://avatars.githubusercontent.com/u/126646?v=4",
         "events_url" : "https://api.github.com/users/laanwj/events{/privacy}",
         "followers_url" : "https://api.github.com/users/laanwj/followers",
         "following_url" : "https://api.github.com/users/laanwj/following{/other_user}",
         "gists_url" : "https://api.github.com/users/laanwj/gists{/gist_id}",
         "gravatar_id" : "",
         "html_url" : "https://github.com/laanwj",
         "id" : 126646,
         "login" : "laanwj",
         "node_id" : "MDQ6VXNlcjEyNjY0Ng==",
         "organizations_url" : "https://api.github.com/users/laanwj/orgs",
         "received_events_url" : "https://api.github.com/users/laanwj/received_events",
         "repos_url" : "https://api.github.com/users/laanwj/repos",
         "site_admin" : false,
         "starred_url" : "https://api.github.com/users/laanwj/starred{/owner}{/repo}",
         "subscriptions_url" : "https://api.github.com/users/laanwj/subscriptions",
         "type" : "User",
         "url" : "https://api.github.com/users/laanwj"
      }
   },
   {
      "_links" : {
         "html" : {
            "href" : "https://github.com/bitcoin/bitcoin/pull/3592#discussion_r9231774"
         },
         "pull_request" : {
            "href" : "https://api.github.com/repos/bitcoin/bitcoin/pulls/3592"
         },
         "self" : {
            "href" : "https://api.github.com/repos/bitcoin/bitcoin/pulls/comments/9231774"
         }
      },
      "author_association" : "MEMBER",
      "body" : "In practice, it's really only seen/used by humans right now. I figured this was a good compromise of consistency between different software, without sacrificing the level of detail bitcoind is able to provide. Replacing the space with a dash/minus sounds like a good improvement to me.\n",
      "commit_id" : "c117d9e93a712c3f1e2001bdb6e20e7a1c5e339b",
      "created_at" : "2014-01-28T16:00:15Z",
      "diff_hunk" : "@@ -605,14 +605,14 @@ bool CheckTransaction(const CTransaction& tx, CValidationState &state)\n     // Basic checks that don't depend on any context\n     if (tx.vin.empty())\n         return state.DoS(10, error(\"CheckTransaction() : vin empty\"),\n-                         REJECT_INVALID, \"vin empty\");\n+                         REJECT_INVALID, \"bad-txns-vin empty\");",
      "html_url" : "https://github.com/bitcoin/bitcoin/pull/3592#discussion_r9231774",
      "id" : 9231774,
      "line" : null,
      "node_id" : "MDI0OlB1bGxSZXF1ZXN0UmV2aWV3Q29tbWVudDkyMzE3NzQ=",
      "original_commit_id" : "0da64dfdb2a41eee2cc4b63703c2962cf269a6ee",
      "original_line" : null,
      "original_position" : 5,
      "original_start_line" : null,
      "path" : "src/main.cpp",
      "position" : null,
      "pull_request_review_id" : null,
      "pull_request_url" : "https://api.github.com/repos/bitcoin/bitcoin/pulls/3592",
      "reactions" : {
         "+1" : 0,
         "-1" : 0,
         "confused" : 0,
         "eyes" : 0,
         "heart" : 0,
         "hooray" : 0,
         "laugh" : 0,
         "rocket" : 0,
         "total_count" : 0,
         "url" : "https://api.github.com/repos/bitcoin/bitcoin/pulls/comments/9231774/reactions"
      },
      "side" : "RIGHT",
      "start_line" : null,
      "start_side" : null,
      "subject_type" : "line",
      "updated_at" : "2014-01-29T17:39:53Z",
      "url" : "https://api.github.com/repos/bitcoin/bitcoin/pulls/comments/9231774",
      "user" : {
         "avatar_url" : "https://avatars.githubusercontent.com/u/1095675?v=4",
         "events_url" : "https://api.github.com/users/luke-jr/events{/privacy}",
         "followers_url" : "https://api.github.com/users/luke-jr/followers",
         "following_url" : "https://api.github.com/users/luke-jr/following{/other_user}",
         "gists_url" : "https://api.github.com/users/luke-jr/gists{/gist_id}",
         "gravatar_id" : "",
         "html_url" : "https://github.com/luke-jr",
         "id" : 1095675,
         "login" : "luke-jr",
         "node_id" : "MDQ6VXNlcjEwOTU2NzU=",
         "organizations_url" : "https://api.github.com/users/luke-jr/orgs",
         "received_events_url" : "https://api.github.com/users/luke-jr/received_events",
         "repos_url" : "https://api.github.com/users/luke-jr/repos",
         "site_admin" : false,
         "starred_url" : "https://api.github.com/users/luke-jr/starred{/owner}{/repo}",
         "subscriptions_url" : "https://api.github.com/users/luke-jr/subscriptions",
         "type" : "User",
         "url" : "https://api.github.com/users/luke-jr"
      }
   },
   {
      "author_association" : "NONE",
      "body" : "Automatic sanity-testing: PASSED, see http://jenkins.bluematt.me/pull-tester/c117d9e93a712c3f1e2001bdb6e20e7a1c5e339b for binaries and test log.\nThis test script verifies pulls every time they are updated. It, however, dies sometimes and fails to test properly.  If you are waiting on a test, please check timestamps to verify that the test.log is moving at http://jenkins.bluematt.me/pull-tester/current/\nContact BlueMatt on freenode if something looks broken.\n",
      "created_at" : "2014-01-29T18:14:34Z",
      "html_url" : "https://github.com/bitcoin/bitcoin/pull/3592#issuecomment-33612817",
      "id" : 33612817,
      "issue_url" : "https://api.github.com/repos/bitcoin/bitcoin/issues/3592",
      "node_id" : "MDEyOklzc3VlQ29tbWVudDMzNjEyODE3",
      "performed_via_github_app" : null,
      "reactions" : {
         "+1" : 0,
         "-1" : 0,
         "confused" : 0,
         "eyes" : 0,
         "heart" : 0,
         "hooray" : 0,
         "laugh" : 0,
         "rocket" : 0,
         "total_count" : 0,
         "url" : "https://api.github.com/repos/bitcoin/bitcoin/issues/comments/33612817/reactions"
      },
      "updated_at" : "2014-01-29T18:14:34Z",
      "url" : "https://api.github.com/repos/bitcoin/bitcoin/issues/comments/33612817",
      "user" : {
         "avatar_url" : "https://avatars.githubusercontent.com/u/2110907?v=4",
         "events_url" : "https://api.github.com/users/BitcoinPullTester/events{/privacy}",
         "followers_url" : "https://api.github.com/users/BitcoinPullTester/followers",
         "following_url" : "https://api.github.com/users/BitcoinPullTester/following{/other_user}",
         "gists_url" : "https://api.github.com/users/BitcoinPullTester/gists{/gist_id}",
         "gravatar_id" : "",
         "html_url" : "https://github.com/BitcoinPullTester",
         "id" : 2110907,
         "login" : "BitcoinPullTester",
         "node_id" : "MDQ6VXNlcjIxMTA5MDc=",
         "organizations_url" : "https://api.github.com/users/BitcoinPullTester/orgs",
         "received_events_url" : "https://api.github.com/users/BitcoinPullTester/received_events",
         "repos_url" : "https://api.github.com/users/BitcoinPullTester/repos",
         "site_admin" : false,
         "starred_url" : "https://api.github.com/users/BitcoinPullTester/starred{/owner}{/repo}",
         "subscriptions_url" : "https://api.github.com/users/BitcoinPullTester/subscriptions",
         "type" : "User",
         "url" : "https://api.github.com/users/BitcoinPullTester"
      }
   },
   {
      "author_association" : "MEMBER",
      "body" : "ACK\n",
      "created_at" : "2014-01-30T07:45:21Z",
      "html_url" : "https://github.com/bitcoin/bitcoin/pull/3592#issuecomment-33666346",
      "id" : 33666346,
      "issue_url" : "https://api.github.com/repos/bitcoin/bitcoin/issues/3592",
      "node_id" : "MDEyOklzc3VlQ29tbWVudDMzNjY2MzQ2",
      "performed_via_github_app" : null,
      "reactions" : {
         "+1" : 0,
         "-1" : 0,
         "confused" : 0,
         "eyes" : 0,
         "heart" : 0,
         "hooray" : 0,
         "laugh" : 0,
         "rocket" : 0,
         "total_count" : 0,
         "url" : "https://api.github.com/repos/bitcoin/bitcoin/issues/comments/33666346/reactions"
      },
      "updated_at" : "2014-01-30T07:45:21Z",
      "url" : "https://api.github.com/repos/bitcoin/bitcoin/issues/comments/33666346",
      "user" : {
         "avatar_url" : "https://avatars.githubusercontent.com/u/126646?v=4",
         "events_url" : "https://api.github.com/users/laanwj/events{/privacy}",
         "followers_url" : "https://api.github.com/users/laanwj/followers",
         "following_url" : "https://api.github.com/users/laanwj/following{/other_user}",
         "gists_url" : "https://api.github.com/users/laanwj/gists{/gist_id}",
         "gravatar_id" : "",
         "html_url" : "https://github.com/laanwj",
         "id" : 126646,
         "login" : "laanwj",
         "node_id" : "MDQ6VXNlcjEyNjY0Ng==",
         "organizations_url" : "https://api.github.com/users/laanwj/orgs",
         "received_events_url" : "https://api.github.com/users/laanwj/received_events",
         "repos_url" : "https://api.github.com/users/laanwj/repos",
         "site_admin" : false,
         "starred_url" : "https://api.github.com/users/laanwj/starred{/owner}{/repo}",
         "subscriptions_url" : "https://api.github.com/users/laanwj/subscriptions",
         "type" : "User",
         "url" : "https://api.github.com/users/laanwj"
      }
   },
   {
      "author_association" : "CONTRIBUTOR",
      "body" : "ACK\n",
      "created_at" : "2014-01-30T14:53:34Z",
      "html_url" : "https://github.com/bitcoin/bitcoin/pull/3592#issuecomment-33694260",
      "id" : 33694260,
      "issue_url" : "https://api.github.com/repos/bitcoin/bitcoin/issues/3592",
      "node_id" : "MDEyOklzc3VlQ29tbWVudDMzNjk0MjYw",
      "performed_via_github_app" : null,
      "reactions" : {
         "+1" : 0,
         "-1" : 0,
         "confused" : 0,
         "eyes" : 0,
         "heart" : 0,
         "hooray" : 0,
         "laugh" : 0,
         "rocket" : 0,
         "total_count" : 0,
         "url" : "https://api.github.com/repos/bitcoin/bitcoin/issues/comments/33694260/reactions"
      },
      "updated_at" : "2014-01-30T14:53:34Z",
      "url" : "https://api.github.com/repos/bitcoin/bitcoin/issues/comments/33694260",
      "user" : {
         "avatar_url" : "https://avatars.githubusercontent.com/u/494411?v=4",
         "events_url" : "https://api.github.com/users/jgarzik/events{/privacy}",
         "followers_url" : "https://api.github.com/users/jgarzik/followers",
         "following_url" : "https://api.github.com/users/jgarzik/following{/other_user}",
         "gists_url" : "https://api.github.com/users/jgarzik/gists{/gist_id}",
         "gravatar_id" : "",
         "html_url" : "https://github.com/jgarzik",
         "id" : 494411,
         "login" : "jgarzik",
         "node_id" : "MDQ6VXNlcjQ5NDQxMQ==",
         "organizations_url" : "https://api.github.com/users/jgarzik/orgs",
         "received_events_url" : "https://api.github.com/users/jgarzik/received_events",
         "repos_url" : "https://api.github.com/users/jgarzik/repos",
         "site_admin" : false,
         "starred_url" : "https://api.github.com/users/jgarzik/starred{/owner}{/repo}",
         "subscriptions_url" : "https://api.github.com/users/jgarzik/subscriptions",
         "type" : "User",
         "url" : "https://api.github.com/users/jgarzik"
      }
   },
   {
      "author_association" : "MEMBER",
      "body" : "ACK\n",
      "created_at" : "2014-01-30T15:37:20Z",
      "html_url" : "https://github.com/bitcoin/bitcoin/pull/3592#issuecomment-33698951",
      "id" : 33698951,
      "issue_url" : "https://api.github.com/repos/bitcoin/bitcoin/issues/3592",
      "node_id" : "MDEyOklzc3VlQ29tbWVudDMzNjk4OTUx",
      "performed_via_github_app" : null,
      "reactions" : {
         "+1" : 0,
         "-1" : 0,
         "confused" : 0,
         "eyes" : 0,
         "heart" : 0,
         "hooray" : 0,
         "laugh" : 0,
         "rocket" : 0,
         "total_count" : 0,
         "url" : "https://api.github.com/repos/bitcoin/bitcoin/issues/comments/33698951/reactions"
      },
      "updated_at" : "2014-01-30T15:37:20Z",
      "url" : "https://api.github.com/repos/bitcoin/bitcoin/issues/comments/33698951",
      "user" : {
         "avatar_url" : "https://avatars.githubusercontent.com/u/548488?v=4",
         "events_url" : "https://api.github.com/users/sipa/events{/privacy}",
         "followers_url" : "https://api.github.com/users/sipa/followers",
         "following_url" : "https://api.github.com/users/sipa/following{/other_user}",
         "gists_url" : "https://api.github.com/users/sipa/gists{/gist_id}",
         "gravatar_id" : "",
         "html_url" : "https://github.com/sipa",
         "id" : 548488,
         "login" : "sipa",
         "node_id" : "MDQ6VXNlcjU0ODQ4OA==",
         "organizations_url" : "https://api.github.com/users/sipa/orgs",
         "received_events_url" : "https://api.github.com/users/sipa/received_events",
         "repos_url" : "https://api.github.com/users/sipa/repos",
         "site_admin" : false,
         "starred_url" : "https://api.github.com/users/sipa/starred{/owner}{/repo}",
         "subscriptions_url" : "https://api.github.com/users/sipa/subscriptions",
         "type" : "User",
         "url" : "https://api.github.com/users/sipa"
      }
   },
   {
      "author_association" : "CONTRIBUTOR",
      "body" : "Can someone post a reference to the BIP 22 document on here please? (and BIP30?)\n",
      "created_at" : "2014-03-27T05:57:52Z",
      "html_url" : "https://github.com/bitcoin/bitcoin/pull/3592#issuecomment-38771510",
      "id" : 38771510,
      "issue_url" : "https://api.github.com/repos/bitcoin/bitcoin/issues/3592",
      "node_id" : "MDEyOklzc3VlQ29tbWVudDM4NzcxNTEw",
      "performed_via_github_app" : null,
      "reactions" : {
         "+1" : 0,
         "-1" : 0,
         "confused" : 0,
         "eyes" : 0,
         "heart" : 0,
         "hooray" : 0,
         "laugh" : 0,
         "rocket" : 0,
         "total_count" : 0,
         "url" : "https://api.github.com/repos/bitcoin/bitcoin/issues/comments/38771510/reactions"
      },
      "updated_at" : "2014-03-27T05:57:52Z",
      "url" : "https://api.github.com/repos/bitcoin/bitcoin/issues/comments/38771510",
      "user" : {
         "avatar_url" : "https://avatars.githubusercontent.com/u/1530283?v=4",
         "events_url" : "https://api.github.com/users/rebroad/events{/privacy}",
         "followers_url" : "https://api.github.com/users/rebroad/followers",
         "following_url" : "https://api.github.com/users/rebroad/following{/other_user}",
         "gists_url" : "https://api.github.com/users/rebroad/gists{/gist_id}",
         "gravatar_id" : "",
         "html_url" : "https://github.com/rebroad",
         "id" : 1530283,
         "login" : "rebroad",
         "node_id" : "MDQ6VXNlcjE1MzAyODM=",
         "organizations_url" : "https://api.github.com/users/rebroad/orgs",
         "received_events_url" : "https://api.github.com/users/rebroad/received_events",
         "repos_url" : "https://api.github.com/users/rebroad/repos",
         "site_admin" : false,
         "starred_url" : "https://api.github.com/users/rebroad/starred{/owner}{/repo}",
         "subscriptions_url" : "https://api.github.com/users/rebroad/subscriptions",
         "type" : "User",
         "url" : "https://api.github.com/users/rebroad"
      }
   },
   {
      "author_association" : "NONE",
      "body" : "[BIP0022](https://github.com/bitcoin/bips/blob/master/bip-0022.mediawiki)\n[BIP0030](https://github.com/bitcoin/bips/blob/master/bip-0030.mediawiki)\n",
      "created_at" : "2014-03-28T19:38:58Z",
      "html_url" : "https://github.com/bitcoin/bitcoin/pull/3592#issuecomment-38959807",
      "id" : 38959807,
      "issue_url" : "https://api.github.com/repos/bitcoin/bitcoin/issues/3592",
      "node_id" : "MDEyOklzc3VlQ29tbWVudDM4OTU5ODA3",
      "performed_via_github_app" : null,
      "reactions" : {
         "+1" : 0,
         "-1" : 0,
         "confused" : 0,
         "eyes" : 0,
         "heart" : 0,
         "hooray" : 0,
         "laugh" : 0,
         "rocket" : 0,
         "total_count" : 0,
         "url" : "https://api.github.com/repos/bitcoin/bitcoin/issues/comments/38959807/reactions"
      },
      "updated_at" : "2014-03-28T19:38:58Z",
      "url" : "https://api.github.com/repos/bitcoin/bitcoin/issues/comments/38959807",
      "user" : {
         "avatar_url" : "https://avatars.githubusercontent.com/u/566354?v=4",
         "events_url" : "https://api.github.com/users/christophebiocca/events{/privacy}",
         "followers_url" : "https://api.github.com/users/christophebiocca/followers",
         "following_url" : "https://api.github.com/users/christophebiocca/following{/other_user}",
         "gists_url" : "https://api.github.com/users/christophebiocca/gists{/gist_id}",
         "gravatar_id" : "",
         "html_url" : "https://github.com/christophebiocca",
         "id" : 566354,
         "login" : "christophebiocca",
         "node_id" : "MDQ6VXNlcjU2NjM1NA==",
         "organizations_url" : "https://api.github.com/users/christophebiocca/orgs",
         "received_events_url" : "https://api.github.com/users/christophebiocca/received_events",
         "repos_url" : "https://api.github.com/users/christophebiocca/repos",
         "site_admin" : false,
         "starred_url" : "https://api.github.com/users/christophebiocca/starred{/owner}{/repo}",
         "subscriptions_url" : "https://api.github.com/users/christophebiocca/subscriptions",
         "type" : "User",
         "url" : "https://api.github.com/users/christophebiocca"
      }
   }
]
