{
   "active_lock_reason" : "resolved",
   "assignee" : null,
   "assignees" : [],
   "author_association" : "NONE",
   "body" : "According to the options model, a restart is required after changing this option. So let's notify the user about it.\n",
   "closed_at" : "2014-04-09T08:34:48Z",
   "closed_by" : {
      "avatar_url" : "https://avatars.githubusercontent.com/u/126646?v=4",
      "events_url" : "https://api.github.com/users/laanwj/events{/privacy}",
      "followers_url" : "https://api.github.com/users/laanwj/followers",
      "following_url" : "https://api.github.com/users/laanwj/following{/other_user}",
      "gists_url" : "https://api.github.com/users/laanwj/gists{/gist_id}",
      "gravatar_id" : "",
      "html_url" : "https://github.com/laanwj",
      "id" : 126646,
      "login" : "laanwj",
      "node_id" : "MDQ6VXNlcjEyNjY0Ng==",
      "organizations_url" : "https://api.github.com/users/laanwj/orgs",
      "received_events_url" : "https://api.github.com/users/laanwj/received_events",
      "repos_url" : "https://api.github.com/users/laanwj/repos",
      "site_admin" : false,
      "starred_url" : "https://api.github.com/users/laanwj/starred{/owner}{/repo}",
      "subscriptions_url" : "https://api.github.com/users/laanwj/subscriptions",
      "type" : "User",
      "url" : "https://api.github.com/users/laanwj"
   },
   "comments" : 2,
   "comments_url" : "https://api.github.com/repos/bitcoin/bitcoin/issues/4020/comments",
   "created_at" : "2014-04-07T17:27:14Z",
   "draft" : false,
   "events_url" : "https://api.github.com/repos/bitcoin/bitcoin/issues/4020/events",
   "html_url" : "https://github.com/bitcoin/bitcoin/pull/4020",
   "id" : 31004329,
   "labels" : [],
   "labels_url" : "https://api.github.com/repos/bitcoin/bitcoin/issues/4020/labels{/name}",
   "locked" : true,
   "milestone" : null,
   "node_id" : "MDExOlB1bGxSZXF1ZXN0MTQ0NTk4NzE=",
   "number" : 4020,
   "performed_via_github_app" : null,
   "pull_request" : {
      "diff_url" : "https://github.com/bitcoin/bitcoin/pull/4020.diff",
      "html_url" : "https://github.com/bitcoin/bitcoin/pull/4020",
      "merged_at" : "2014-04-09T08:34:48Z",
      "patch_url" : "https://github.com/bitcoin/bitcoin/pull/4020.patch",
      "url" : "https://api.github.com/repos/bitcoin/bitcoin/pulls/4020"
   },
   "reactions" : {
      "+1" : 0,
      "-1" : 0,
      "confused" : 0,
      "eyes" : 0,
      "heart" : 0,
      "hooray" : 0,
      "laugh" : 0,
      "rocket" : 0,
      "total_count" : 0,
      "url" : "https://api.github.com/repos/bitcoin/bitcoin/issues/4020/reactions"
   },
   "repository_url" : "https://api.github.com/repos/bitcoin/bitcoin",
   "state" : "closed",
   "state_reason" : null,
   "timeline_url" : "https://api.github.com/repos/bitcoin/bitcoin/issues/4020/timeline",
   "title" : "Restart-warning for spendZeroConfChange option",
   "updated_at" : "2021-09-08T10:33:25Z",
   "url" : "https://api.github.com/repos/bitcoin/bitcoin/issues/4020",
   "user" : {
      "avatar_url" : "https://avatars.githubusercontent.com/u/5160000?v=4",
      "events_url" : "https://api.github.com/users/langerhans/events{/privacy}",
      "followers_url" : "https://api.github.com/users/langerhans/followers",
      "following_url" : "https://api.github.com/users/langerhans/following{/other_user}",
      "gists_url" : "https://api.github.com/users/langerhans/gists{/gist_id}",
      "gravatar_id" : "",
      "html_url" : "https://github.com/langerhans",
      "id" : 5160000,
      "login" : "langerhans",
      "node_id" : "MDQ6VXNlcjUxNjAwMDA=",
      "organizations_url" : "https://api.github.com/users/langerhans/orgs",
      "received_events_url" : "https://api.github.com/users/langerhans/received_events",
      "repos_url" : "https://api.github.com/users/langerhans/repos",
      "site_admin" : false,
      "starred_url" : "https://api.github.com/users/langerhans/starred{/owner}{/repo}",
      "subscriptions_url" : "https://api.github.com/users/langerhans/subscriptions",
      "type" : "User",
      "url" : "https://api.github.com/users/langerhans"
   }
}
